README.md
setup.cfg
setup.py
mlrose_hiive/__init__.py
mlrose_hiive.egg-info/PKG-INFO
mlrose_hiive.egg-info/SOURCES.txt
mlrose_hiive.egg-info/dependency_links.txt
mlrose_hiive.egg-info/not-zip-safe
mlrose_hiive.egg-info/requires.txt
mlrose_hiive.egg-info/top_level.txt
mlrose_hiive/algorithms/__init__.py
mlrose_hiive/algorithms/ga.py
mlrose_hiive/algorithms/gd.py
mlrose_hiive/algorithms/hc.py
mlrose_hiive/algorithms/mimic.py
mlrose_hiive/algorithms/rhc.py
mlrose_hiive/algorithms/sa.py
mlrose_hiive/algorithms/crossovers/__init__.py
mlrose_hiive/algorithms/crossovers/_crossover_base.py
mlrose_hiive/algorithms/crossovers/one_point_crossover.py
mlrose_hiive/algorithms/crossovers/tsp_crossover.py
mlrose_hiive/algorithms/crossovers/uniform_crossover.py
mlrose_hiive/algorithms/decay/__init__.py
mlrose_hiive/algorithms/decay/arith_decay.py
mlrose_hiive/algorithms/decay/custom_schedule.py
mlrose_hiive/algorithms/decay/exp_decay.py
mlrose_hiive/algorithms/decay/geom_decay.py
mlrose_hiive/algorithms/mutators/__init__.py
mlrose_hiive/algorithms/mutators/_mutator_base.py
mlrose_hiive/algorithms/mutators/change_one_mutator.py
mlrose_hiive/algorithms/mutators/discrete_mutator.py
mlrose_hiive/algorithms/mutators/shift_one_mutator.py
mlrose_hiive/algorithms/mutators/swap_mutator.py
mlrose_hiive/decorators/__init__.py
mlrose_hiive/decorators/short_name_decorator.py
mlrose_hiive/fitness/__init__.py
mlrose_hiive/fitness/_discrete_peaks_base.py
mlrose_hiive/fitness/continuous_peaks.py
mlrose_hiive/fitness/custom_fitness.py
mlrose_hiive/fitness/flip_flop.py
mlrose_hiive/fitness/four_peaks.py
mlrose_hiive/fitness/knapsack.py
mlrose_hiive/fitness/max_k_color.py
mlrose_hiive/fitness/one_max.py
mlrose_hiive/fitness/queens.py
mlrose_hiive/fitness/six_peaks.py
mlrose_hiive/fitness/travelling_sales.py
mlrose_hiive/generators/__init__.py
mlrose_hiive/generators/flip_flop_generator.py
mlrose_hiive/generators/knapsack_generator.py
mlrose_hiive/generators/max_k_color_generator.py
mlrose_hiive/generators/queens_generator.py
mlrose_hiive/generators/tsp_generator.py
mlrose_hiive/gridsearch/__init__.py
mlrose_hiive/gridsearch/grid_search_mixin.py
mlrose_hiive/neural/__init__.py
mlrose_hiive/neural/_nn_base.py
