Metadata-Version: 2.1
Name: mlrose-hiive
Version: 2.1.1
Summary: MLROSe: Machine Learning, Randomized Optimization and Search (hiive extended remix)
Home-page: https://github.com/hiive/mlrose
Author: Genevieve Hayes (modified by Andrew Rollings)
License: BSD
Download-URL: https://github.com/hiive/mlrose/archive/2.1.1.tar.gz
Platform: UNKNOWN
Classifier: Intended Audience :: Education
Classifier: Intended Audience :: Science/Research
Classifier: Natural Language :: English
Classifier: License :: OSI Approved :: BSD License
Classifier: Programming Language :: Python
Classifier: Programming Language :: Python :: 3
Classifier: Topic :: Scientific/Engineering
Classifier: Topic :: Scientific/Engineering :: Artificial Intelligence
Classifier: Topic :: Scientific/Engineering :: Mathematics
Classifier: Topic :: Software Development :: Libraries
Classifier: Topic :: Software Development :: Libraries :: Python Modules
Requires-Python: >=3
